eventz/__init__.py
eventz/aggregate.py
eventz/aggregate_builder.py
eventz/dummy_storage.py
eventz/entity.py
eventz/errors.py
eventz/event_store.py
eventz/event_store_json_file.py
eventz/immutable.py
eventz/immutable_sequence.py
eventz/marshall.py
eventz/messages.py
eventz/protocols.py
eventz/repository.py
eventz/service.py
eventz/value_object.py
eventz-0.3.0.dist-info/LICENSE
eventz-0.3.0.dist-info/WHEEL
eventz-0.3.0.dist-info/METADATA
eventz-0.3.0.dist-info/RECORD
