Metadata-Version: 2.1
Name: eventz
Version: 0.3.0
Summary: Eventz: an event-centric microframework.
Author: Dan Ballance
Author-email: work@danballance.uk
Requires-Python: >=3.8,<4.0
Classifier: Programming Language :: Python :: 3
Classifier: Programming Language :: Python :: 3.8
Requires-Dist: immutables (>=0.14,<0.15)
Requires-Dist: python-dateutil (>=2.8.1,<3.0.0)
